account/__init__.py
account/first.py
psp_account-0.1.dist-info/License.txt
psp_account-0.1.dist-info/METADATA
psp_account-0.1.dist-info/WHEEL
psp_account-0.1.dist-info/top_level.txt
psp_account-0.1.dist-info/RECORD
