Metadata-Version: 2.1
Name: psp-account
Version: 0.1
Summary: OOP-based banking system
Author: Prathamesh72
Author-email: pspwork72@gmail.com
License: MIT
License-File: License.txt
Requires-Dist: pandas
